Metadata-Version: 1.0
Name: mytestlib-testlib
Version: 1.0.0
Summary: My Test Library.
Home-page: UNKNOWN
Author: KanKazumasa
Author-email: terrier.clan.d@gmail.com
License: UNKNOWN
Platform: UNKNOWN
